RsCmwGprfMeas/RsCmwGprfMeas.py
RsCmwGprfMeas/__init__.py
RsCmwGprfMeas/enums.py
RsCmwGprfMeas/repcap.py
RsCmwGprfMeas/CustomFiles/__init__.py
RsCmwGprfMeas/CustomFiles/events.py
RsCmwGprfMeas/CustomFiles/reliability.py
RsCmwGprfMeas/CustomFiles/utilities.py
RsCmwGprfMeas/Implementations/__init__.py
RsCmwGprfMeas/Implementations/Calibration/__init__.py
RsCmwGprfMeas/Implementations/Calibration/ExtPwrSensor/Zero.py
RsCmwGprfMeas/Implementations/Calibration/ExtPwrSensor/__init__.py
RsCmwGprfMeas/Implementations/Canalyzer/__init__.py
RsCmwGprfMeas/Implementations/Canalyzer/State/All.py
RsCmwGprfMeas/Implementations/Canalyzer/State/__init__.py
RsCmwGprfMeas/Implementations/Configure/__init__.py
RsCmwGprfMeas/Implementations/Configure/Canalyzer/IqFile.py
RsCmwGprfMeas/Implementations/Configure/Canalyzer/Sall.py
RsCmwGprfMeas/Implementations/Configure/Canalyzer/__init__.py
RsCmwGprfMeas/Implementations/Configure/ExtPwrSensor/Attenuation.py
RsCmwGprfMeas/Implementations/Configure/ExtPwrSensor/__init__.py
RsCmwGprfMeas/Implementations/Configure/FftSpecAn/PeakSearch.py
RsCmwGprfMeas/Implementations/Configure/FftSpecAn/__init__.py
RsCmwGprfMeas/Implementations/Configure/IqRecorder/Capture.py
RsCmwGprfMeas/Implementations/Configure/IqRecorder/Trigger.py
RsCmwGprfMeas/Implementations/Configure/IqRecorder/__init__.py
RsCmwGprfMeas/Implementations/Configure/IqRecorder/FilterPy/Bandpass.py
RsCmwGprfMeas/Implementations/Configure/IqRecorder/FilterPy/Gauss.py
RsCmwGprfMeas/Implementations/Configure/IqRecorder/FilterPy/__init__.py
RsCmwGprfMeas/Implementations/Configure/IqRecorder/ListPy/EnvelopePower.py
RsCmwGprfMeas/Implementations/Configure/IqRecorder/ListPy/Frequency.py
RsCmwGprfMeas/Implementations/Configure/IqRecorder/ListPy/Sstop.py
RsCmwGprfMeas/Implementations/Configure/IqRecorder/ListPy/__init__.py
RsCmwGprfMeas/Implementations/Configure/IqVsSlot/Trigger.py
RsCmwGprfMeas/Implementations/Configure/IqVsSlot/__init__.py
RsCmwGprfMeas-4.0.140.dist-info/METADATA
RsCmwGprfMeas-4.0.140.dist-info/WHEEL
RsCmwGprfMeas-4.0.140.dist-info/top_level.txt
RsCmwGprfMeas-4.0.140.dist-info/RECORD
